firemon_api/__init__.py
firemon_api/apps/__init__.py
firemon_api/apps/controlpanel/__init__.py
firemon_api/apps/controlpanel/certauth.py
firemon_api/apps/controlpanel/cleanup.py
firemon_api/apps/controlpanel/config.py
firemon_api/apps/controlpanel/database.py
firemon_api/apps/controlpanel/diagpkg.py
firemon_api/apps/orchestration/__init__.py
firemon_api/apps/orchestration/changes.py
firemon_api/apps/policyoptimizer/__init__.py
firemon_api/apps/policyplanner/__init__.py
firemon_api/apps/policyplanner/packets.py
firemon_api/apps/policyplanner/policyplan.py
firemon_api/apps/policyplanner/siql.py
firemon_api/apps/policyplanner/tasks.py
firemon_api/apps/policyplanner/workflows.py
firemon_api/apps/securitymanager/__init__.py
firemon_api/apps/securitymanager/access_path.py
firemon_api/apps/securitymanager/centralsyslogconfigs.py
firemon_api/apps/securitymanager/centralsyslogs.py
firemon_api/apps/securitymanager/collectionconfigs.py
firemon_api/apps/securitymanager/collectors.py
firemon_api/apps/securitymanager/deviceclusters.py
firemon_api/apps/securitymanager/devicegroups.py
firemon_api/apps/securitymanager/devicepacks.py
firemon_api/apps/securitymanager/devices.py
firemon_api/apps/securitymanager/elasticsearch.py
firemon_api/apps/securitymanager/license.py
firemon_api/apps/securitymanager/logging.py
firemon_api/apps/securitymanager/maps.py
firemon_api/apps/securitymanager/networksegments.py
firemon_api/apps/securitymanager/revisions.py
firemon_api/apps/securitymanager/routes.py
firemon_api/apps/securitymanager/rulerec.py
firemon_api/apps/securitymanager/siql.py
firemon_api/apps/securitymanager/users.py
firemon_api/apps/securitymanager/zones.py
firemon_api/apps/structure/__init__.py
firemon_api/apps/structure/apa.py
firemon_api/apps/structure/collector.py
firemon_api/apps/structure/device.py
firemon_api/apps/structure/policyplan.py
firemon_api/apps/structure/rulerec.py
firemon_api/core/__init__.py
firemon_api/core/api.py
firemon_api/core/app.py
firemon_api-0.3.9.dist-info/METADATA
firemon_api-0.3.9.dist-info/WHEEL
firemon_api-0.3.9.dist-info/top_level.txt
firemon_api-0.3.9.dist-info/RECORD
