Metadata-Version: 2.4
Name: firemon-api
Version: 0.3.9
Summary: Python Wrapper for Firemon APIs
Author-email: Luke Johannsen <luke.johannsen@firemon.com>
License: MIT License
Project-URL: Documentation, https://firemon-api.readthedocs.io/en/latest/
Project-URL: Repository, https://github.com/lukejohannsen/firemon-api
Keywords: firemon,api,development
Classifier: Development Status :: 4 - Beta
Classifier: Intended Audience :: Developers
Classifier: Topic :: Software Development
Classifier: License :: OSI Approved :: MIT License
Classifier: Programming Language :: Python :: 3
Classifier: Programming Language :: Python :: 3.8
Classifier: Programming Language :: Python :: 3.9
Classifier: Programming Language :: Python :: 3.10
Classifier: Programming Language :: Python :: 3.11
Classifier: Programming Language :: Python :: 3.12
Requires-Python: >=3.8
Requires-Dist: chardet
Requires-Dist: requests
Requires-Dist: tenacity
